wtpsplit_lite/__init__.py
wtpsplit_lite/_config.py
wtpsplit_lite/_extract.py
wtpsplit_lite/_sat.py
wtpsplit_lite/_tokenizer.py
wtpsplit_lite/_utils.py
wtpsplit_lite/py.typed
wtpsplit_lite-0.2.0.dist-info/METADATA
wtpsplit_lite-0.2.0.dist-info/WHEEL
wtpsplit_lite-0.2.0.dist-info/licenses/LICENSE
wtpsplit_lite-0.2.0.dist-info/RECORD
