Metadata-Version: 2.4
Name: wtpsplit-lite
Version: 0.2.0
Summary: wtpsplit with minimal dependencies
Project-URL: homepage, https://github.com/superlinear-ai/wtpsplit-lite
Project-URL: source, https://github.com/superlinear-ai/wtpsplit-lite
Project-URL: changelog, https://github.com/superlinear-ai/wtpsplit-lite/blob/main/CHANGELOG.md
Project-URL: releasenotes, https://github.com/superlinear-ai/wtpsplit-lite/releases
Project-URL: documentation, https://github.com/superlinear-ai/wtpsplit-lite
Project-URL: issues, https://github.com/superlinear-ai/wtpsplit-lite/issues
Author-email: Laurent Sorber <laurent@superlinear.eu>
License-File: LICENSE
Requires-Python: <4.0,>=3.10
Requires-Dist: huggingface-hub>=0.25.2
Requires-Dist: numpy>=1.26.0
Requires-Dist: onnxruntime>=1.17.0
Requires-Dist: tokenizers>=0.20
